Workbook
Name Slicer_Category: #N/A
Name Slicer_Month: #N/A
Name Slicer_Year: #N/A

Sheet Data
A1: Order Date | B1: Customer Name | C1: State | D1: Category | E1: Sub-Category | F1: Product Name | G1: Sales | H1: Quantity | I1: Profit | J1: Month | K1: Year
A2: 44199 | B2: Darren Powers | C2: Texas | D2: Office Supplies | E2: Paper | F2: Message Book, Wirebound, Four 5 1/2" X 4" Forms/Pg., 200 Dupl. Sets/Book | G2: 16.45 | H2: 2 | I2: 5.55 | J2: Jan | K2: 2021
A3: 44200 | B3: Phillina Ober | C3: Illinois | D3: Office Supplies | E3: Labels | F3: Avery 508 | G3: 11.78 | H3: 3 | I3: 4.27 | J3: Jan | K3: 2021
A4: 44200 | B4: Phillina Ober | C4: Illinois | D4: Office Supplies | E4: Storage | F4: SAFCO Boltless Steel Shelving | G4: 272.74 | H4: 3 | I4: -64.77 | J4: Jan | K4: 2021
A5: 44200 | B5: Phillina Ober | C5: Illinois | D5: Office Supplies | E5: Binders | F5: GBC Standard Plastic Binding Systems Combs | G5: 3.54 | H5: 2 | I5: -5.49 | J5: Jan | K5: 2021
A6: 44201 | B6: Mick Brown | C6: Pennsylvania | D6: Office Supplies | E6: Art | F6: Avery Hi-Liter EverBold Pen Style Fluorescent Highlighters, 4/Pack | G6: 19.54 | H6: 3 | I6: 4.88 | J6: Jan | K6: 2021
A7: 44202 | B7: Lycoris Saunders | C7: California | D7: Office Supplies | E7: Paper | F7: Xerox 225 | G7: 19.44 | H7: 3 | I7: 9.33 | J7: Jan | K7: 2021
A8: 44202 | B8: Jack O'Briant | C8: Georgia | D8: Office Supplies | E8: Art | F8: Dixon Prang Watercolor Pencils, 10-Color Set with Brush | G8: 12.78 | H8: 3 | I8: 5.24 | J8: Jan | K8: 2021
A9: 44202 | B9: Maria Etezadi | C9: Kentucky | D9: Furniture | E9: Chairs | F9: Global Deluxe High-Back Manager's Chair | G9: 2573.82 | H9: 9 | I9: 746.41 | J9: Jan | K9: 2021
A10: 44202 | B10: Maria Etezadi | C10: Kentucky | D10: Office Supplies | E10: Binders | F10: Ibico Hi-Tech Manual Binding System | G10: 609.98 | H10: 2 | I10: 274.49 | J10: Jan | K10: 2021
A11: 44202 | B11: Maria Etezadi | C11: Kentucky | D11: Office Supplies | E11: Art | F11: Rogers Handheld Barrel Pencil Sharpener | G11: 5.48 | H11: 2 | I11: 1.48 | J11: Jan | K11: 2021
A12: 44202 | B12: Maria Etezadi | C12: Kentucky | D12: Technology | E12: Phones | F12: GE 30524EE4 | G12: 391.98 | H12: 2 | I12: 113.67 | J12: Jan | K12: 2021
A13: 44202 | B13: Maria Etezadi | C13: Kentucky | D13: Technology | E13: Phones | F13: Wireless Extenders zBoost YX545 SOHO Signal Booster | G13: 755.96 | H13: 4 | I13: 204.11 | J13: Jan | K13: 2021
... A8315: 45535 | B8315: Maxwell Schwartz | C8315: California | D8315: Office Supplies | E8315: Storage | F8315: Space Solutions Commercial Steel Shelving | G8315: 193.95 | H8315: 3 | I8315: 9.7 | J8315: Aug | K8315: 2024

Sheet Pivot Table
B3: Total Sales | D3: Profit by Year | K3: Sales by Sub-Category | Q3: Customer Count by Year
B4: Sum of Sales | D4: Sum of Profit | E4: Column Labels | K4: Sub-Categories | L4: Sum of Sales | N4: Category | O4: Sales | Q4: Year | R4: Count of Customers | W4: Top 5 Customers Profit | Z4: Sales by Month
B5: 1928887.9 | D5: Year | E5: Furniture | F5: Office Supplies | G5: Technology | H5: Grand Total | K5: Phones | L5: 279464.42 | N5: =K5 -> Phones | O5: =GETPIVOTDATA("Sales",'Pivot Table'!K5,"Sub-Category",'Pivot Table'!K5) -> 279464.42 | Q5: 2021 | R5: 595 | W5: Row Labels | X5: Sum of Profit | Z5: Row Labels | AA5: Sum of Sales
B6: =GETPIVOTDATA("Sales",$B$4) -> 1928887.9 | D6: 2021 | E6: 5469.77 | F6: 22593.4 | G6: 21492.95 | H6: 49556.12 | K6: Chairs | L6: 277058.98 | N6: =K6 -> Chairs | O6: =GETPIVOTDATA("Sales",'Pivot Table'!K6,"Sub-Category",'Pivot Table'!K6) -> 277058.98 | Q6: 2022 | R6: 573 | W6: Martinez | X6: 3883.09 | Z6: Jan | AA6: 94924.87
D7: 2022 | E7: 3015.17 | F7: 25099.55 | G7: 33503.97 | H7: 61618.69 | K7: Storage | L7: 190679.61 | N7: =K7 -> Storage | O7: =GETPIVOTDATA("Sales",'Pivot Table'!K7,"Sub-Category",'Pivot Table'!K7) -> 190679.61 | Q7: 2023 | R7: 638 | W7: Adrian Barton | X7: 5202.84 | Z7: Feb | AA7: 59640.16
D8: 2023 | E8: 6959.93 | F8: 35052.91 | G8: 39774.1 | H8: 81786.94 | K8: Binders | L8: 169089.73 | N8: =K8 -> Binders | O8: =GETPIVOTDATA("Sales",'Pivot Table'!K8,"Sub-Category",'Pivot Table'!K8) -> 169089.73 | Q8: 2024 | R8: 513 | W8: Sanjit Chand | X8: 5757.42 | Z8: Mar | AA8: 205005.51
D9: 2024 | E9: 2443.8 | F9: 25464.81 | G9: 27090.71 | H9: 54999.32 | K9: Tables | L9: 167672.76 | N9: =K9 -> Tables | O9: =GETPIVOTDATA("Sales",'Pivot Table'!K9,"Sub-Category",'Pivot Table'!K9) -> 167672.76 | Q9: Grand Total | R9: 2319 | W9: Raymond Buch | X9: 6939.17 | Z9: Apr | AA9: 137480.79
D10: Grand Total | E10: 17888.67 | F10: 108210.67 | G10: 121861.73 | H10: 247961.07 | K10: Machines | L10: 166777.78 | N10: =K10 -> Machines | O10: =GETPIVOTDATA("Sales",'Pivot Table'!K10,"Sub-Category",'Pivot Table'!K10) -> 166777.78 | W10: Tamara Chand | X10: 8981.32 | Z10: May | AA10: 155028.83
B11: Total Profit | K11: Accessories | L11: 139241.71 | N11: =K11 -> Accessories | O11: =GETPIVOTDATA("Sales",'Pivot Table'!K11,"Sub-Category",'Pivot Table'!K11) -> 139241.71 | W11: Grand Total | X11: 30763.84 | Z11: Jun | AA11: 152718.72
B12: Sum of Profit | K12: Copiers | L12: 118968.24 | N12: =K12 -> Copiers | O12: =GETPIVOTDATA("Sales",'Pivot Table'!K12,"Sub-Category",'Pivot Table'!K12) -> 118968.24 | Z12: Jul | AA12: 147238.11
B13: 247961.07 | K13: Bookcases | L13: 101387.67 | N13: =K13 -> Bookcases | O13: =GETPIVOTDATA("Sales",'Pivot Table'!K13,"Sub-Category",'Pivot Table'!K13) -> 101387.67 | Q13: Sales by State | Z13: Aug | AA13: 159043.99
B14: =GETPIVOTDATA("Profit",$B$12) -> 247961.07 | K14: Appliances | L14: 87846.1 | N14: =K14 -> Appliances | O14: =GETPIVOTDATA("Sales",'Pivot Table'!K14,"Sub-Category",'Pivot Table'!K14) -> 87846.1 | Q14: Row Labels | R14: Sum of Sales | T14: State | U14: Sales | Z14: Sep | AA14: 219783.3
K15: Furnishings | L15: 76222.69 | N15: =K15 -> Furnishings | O15: =GETPIVOTDATA("Sales",'Pivot Table'!K15,"Sub-Category",'Pivot Table'!K15) -> 76222.69 | Q15: Alabama | R15: 18299.32 | T15: =Q15 -> Alabama | U15: =GETPIVOTDATA("Sales",Q15,"State",Q15) -> 18299.32 | Z15: Oct | AA15: 122546.07
K16: Paper | L16: 64529.99 | N16: =K16 -> Paper | O16: =GETPIVOTDATA("Sales",'Pivot Table'!K16,"Sub-Category",'Pivot Table'!K16) -> 64529.99 | Q16: Arizona | R16: 28978.85 | T16: =Q16 -> Arizona | U16: =GETPIVOTDATA("Sales",Q16,"State",Q16) -> 28978.85 | Z16: Nov | AA16: 234013.28
K17: Supplies | L17: 38554.81 | N17: =K17 -> Supplies | O17: =GETPIVOTDATA("Sales",'Pivot Table'!K17,"Sub-Category",'Pivot Table'!K17) -> 38554.81 | Q17: Arkansas | R17: 9177.42 | T17: =Q17 -> Arkansas | U17: =GETPIVOTDATA("Sales",Q17,"State",Q17) -> 9177.42 | Z17: Dec | AA17: 241464.23
K18: Art | L18: 23145.5 | N18: =K18 -> Art | O18: =GETPIVOTDATA("Sales",'Pivot Table'!K18,"Sub-Category",'Pivot Table'!K18) -> 23145.5 | Q18: California | R18: 390145.54 | T18: =Q18 -> California | U18: =GETPIVOTDATA("Sales",Q18,"State",Q18) -> 390145.54 | Z18: Grand Total | AA18: 1928887.9
K19: Envelopes | L19: 14717.39 | N19: =K19 -> Envelopes | O19: =GETPIVOTDATA("Sales",'Pivot Table'!K19,"Sub-Category",'Pivot Table'!K19) -> 14717.39 | Q19: Colorado | R19: 27113.92 | T19: =Q19 -> Colorado | U19: =GETPIVOTDATA("Sales",Q19,"State",Q19) -> 27113.92
K20: Labels | L20: 11045.55 | N20: =K20 -> Labels | O20: =GETPIVOTDATA("Sales",'Pivot Table'!K20,"Sub-Category",'Pivot Table'!K20) -> 11045.55 | Q20: Connecticut | R20: 11471.42 | T20: =Q20 -> Connecticut | U20: =GETPIVOTDATA("Sales",Q20,"State",Q20) -> 11471.42
K21: Fasteners | L21: 2484.93 | N21: =K21 -> Fasteners | O21: =GETPIVOTDATA("Sales",'Pivot Table'!K21,"Sub-Category",'Pivot Table'!K21) -> 2484.93 | Q21: Delaware | R21: 16302.24 | T21: =Q21 -> Delaware | U21: =GETPIVOTDATA("Sales",Q21,"State",Q21) -> 16302.24
K22: Grand Total | L22: 1928887.9 | Q22: District of Columbia | R22: 2865.02 | T22: =Q22 -> District of Columbia | U22: =GETPIVOTDATA("Sales",Q22,"State",Q22) -> 2865.02
Q23: Florida | R23: 79303.61 | T23: =Q23 -> Florida | U23: =GETPIVOTDATA("Sales",Q23,"State",Q23) -> 79303.61
Q24: Georgia | R24: 46346.2 | T24: =Q24 -> Georgia | U24: =GETPIVOTDATA("Sales",Q24,"State",Q24) -> 46346.2
Q25: Idaho | R25: 3963.47 | T25: =Q25 -> Idaho | U25: =GETPIVOTDATA("Sales",Q25,"State",Q25) -> 3963.47
Q26: Illinois | R26: 68565.03 | T26: =Q26 -> Illinois | U26: =GETPIVOTDATA("Sales",Q26,"State",Q26) -> 68565.03
Q27: Indiana | R27: 47809.55 | T27: =Q27 -> Indiana | U27: =GETPIVOTDATA("Sales",Q27,"State",Q27) -> 47809.55
Q28: Iowa | R28: 4476.41 | T28: =Q28 -> Iowa | U28: =GETPIVOTDATA("Sales",Q28,"State",Q28) -> 4476.41
Q29: Kansas | R29: 2835 | T29: =Q29 -> Kansas | U29: =GETPIVOTDATA("Sales",Q29,"State",Q29) -> 2835
Q30: Kentucky | R30: 23650.59 | T30: =Q30 -> Kentucky | U30: =GETPIVOTDATA("Sales",Q30,"State",Q30) -> 23650.59
Q31: Louisiana | R31: 5297.05 | T31: =Q31 -> Louisiana | U31: =GETPIVOTDATA("Sales",Q31,"State",Q31) -> 5297.05
Q32: Maine | R32: 1270.53 | T32: =Q32 -> Maine | U32: =GETPIVOTDATA("Sales",Q32,"State",Q32) -> 1270.53
Q33: Maryland | R33: 18580.9 | T33: =Q33 -> Maryland | U33: =GETPIVOTDATA("Sales",Q33,"State",Q33) -> 18580.9
Q34: Massachusetts | R34: 23040.06 | T34: =Q34 -> Massachusetts | U34: =GETPIVOTDATA("Sales",Q34,"State",Q34) -> 23040.06
... Q63: Wyoming | R63: 1603.14 | T63: =Q63 -> Wyoming | U63: =GETPIVOTDATA("Sales",Q63,"State",Q63) -> 1603.14
Q64: Grand Total | R64: 1928887.9

Sheet Dashboard
